evalpy/__init__.py
evalpy/cli.py
evalpy/project/__init__.py
evalpy/project/client.py
evalpy/project/db_session.py
evalpy/project/sql_utilities.py
evalpy/visualization/__init__.py
evalpy/visualization/backend.py
evalpy/visualization/icons8-flip-chart-96.png
evalpy/visualization/interface.ui
evalpy/visualization/pyqt_entry.py
evalpy/visualization/window.py
evalpy-0.0.10.dist-info/LICENSE
evalpy-0.0.10.dist-info/METADATA
evalpy-0.0.10.dist-info/WHEEL
evalpy-0.0.10.dist-info/entry_points.txt
evalpy-0.0.10.dist-info/top_level.txt
evalpy-0.0.10.dist-info/RECORD
