Metadata-Version: 2.1
Name: evalpy
Version: 0.0.10
Summary: A lightweight framework for experiment logging and automatic visualization
Home-page: https://github.com/DavidRother/evalpy
Author: David Rother
Author-email: david@edv-drucksysteme.de
License: UNKNOWN
Platform: UNKNOWN
Classifier: Programming Language :: Python :: 3.7
Classifier: License :: OSI Approved :: MIT License
Classifier: Operating System :: OS Independent
Requires-Python: >=3.6
Requires-Dist: click (>=7.0)
Requires-Dist: pyqt5 (>=5.9.2)
Requires-Dist: pyqtgraph (>=0.10.0)
Requires-Dist: pandas (>=0.23.0)
